Lab2/Codigo/sumador_1bit.v
module sumador_1bit (
    input  A,
    input  B,
    input  Ci,
    output So,
    output Co
);

    assign So = A ^ B ^ Ci;
    assign Co = (A & B) | (Ci & (A ^ B));

endmodule

Lab2/Codigo/tb_sumador_1bit.v
`timescale 1ns/1ps

module tb_sumador_1bit;

    reg A;
    reg B;
    reg Ci;

    wire So;
    wire Co;

    sumador_1bit uut (
        .A(A),
        .B(B),
        .Ci(Ci),
        .So(So),
        .Co(Co)
    );

    initial begin
        $dumpfile("sumador_1bit.vcd");
        $dumpvars(0, tb_sumador_1bit);

        $monitor("A=%b B=%b Ci=%b | Co=%b So=%b",
                 A, B, Ci, Co, So);

        A = 0; B = 0; Ci = 0;
        #10;

        A = 0; B = 0; Ci = 1;
        #10;

        A = 0; B = 1; Ci = 0;
        #10;

        A = 0; B = 1; Ci = 1;
        #10;

        A = 1; B = 0; Ci = 0;
        #10;

        A = 1; B = 0; Ci = 1;
        #10;

        A = 1; B = 1; Ci = 0;
        #10;

        A = 1; B = 1; Ci = 1;
        #10;

        $finish;

    end

endmodule

Lab2/Codigo/sumador_1bit.vcd
$date
	Sun Sep 27 11:37:31 2026
$end
$version
	Icarus Verilog
$end
$timescale
	1ps
$end
$scope module tb_sumador_1bit $end
$var wire 1 ! So $end
$var wire 1 " Co $end
$var reg 1 # A $end
$var reg 1 $ B $end
$var reg 1 % Ci $end
$scope module uut $end
$var wire 1 # A $end
$var wire 1 $ B $end
$var wire 1 % Ci $end
$var wire 1 " Co $end
$var wire 1 ! So $end
$upscope $end
$upscope $end
$enddefinitions $end
$comment Show the parameter values. $end
$dumpall
$end
#0
$dumpvars
0%
0$
0#
0"
0!
$end
#10000
1!
1%
#20000
0%
1$
#30000
1"
0!
1%
#40000
0"
1!
0%
0$
1#
#50000
1"
0!
1%
#60000
0%
1$
#70000
1!
1%
